{"data":{"allMarkdownRemark":{"totalCount":6,"edges":[{"node":{"id":"7dfbb9da-5127-5b29-a87d-d8a9244551cf","frontmatter":{"title":"Leaving Gmail","date":"May 24th 2019","author":null,"tags":["web","tech"],"category":"privacy"},"fields":{"slug":"leaving-gmail"},"excerpt":"\nGMail was a revolution in 2004. Is Google too big now ?\n\n"}},{"node":{"id":"e0dcdfce-eb36-5621-9cc8-f490735bd3eb","frontmatter":{"title":"Starting Redux","date":"Nov 17th 2018","author":null,"tags":["javascript","hard","front"],"category":"javascript"},"fields":{"slug":"starting-redux"},"excerpt":"\n3 principles in Redux\n"}},{"node":{"id":"9a375c67-4fed-54a2-a7e3-22a1e982a3f1","frontmatter":{"title":"Hyperledger Blockchain","date":"Nov 7th 2018","author":"Nicolas Zozol","tags":["blockchain","hard","back","architecture"],"category":"blockchain"},"fields":{"slug":"hyperledger-blockchain"},"excerpt":"\nHyperLedger, powered by IBM, is a set of tools for creating your own blockchain.\n\n"}}]}}}